MicrosoftEasterEggs/CommandLine.py
MicrosoftEasterEggs/windows31/__init__.py
MicrosoftEasterEggs/windows31/credits/__init__.py
MicrosoftEasterEggs/windows31/credits/resources/__init__.py
MicrosoftEasterEggs/windows31/credits/resources/emcees.py
MicrosoftEasterEggs/windows31/credits/resources/flag.py
MicrosoftEasterEggs/windows31/credits/resources/text.py
MicrosoftEasterEggs-0.9.1.dist-info/LICENSE
MicrosoftEasterEggs-0.9.1.dist-info/METADATA
MicrosoftEasterEggs-0.9.1.dist-info/WHEEL
MicrosoftEasterEggs-0.9.1.dist-info/entry_points.txt
MicrosoftEasterEggs-0.9.1.dist-info/top_level.txt
MicrosoftEasterEggs-0.9.1.dist-info/RECORD
