Metadata-Version: 2.1
Name: MicrosoftEasterEggs
Version: 0.9.1
Summary: Tools for extracting assets from easter eggs in Microsoft projects
Author: npjg
License: MIT License
Project-URL: Homepage, https://github.com/npjg/microsoft-easter-eggs
Keywords: microsoft,reverse-engineering
Classifier: License :: OSI Approved :: MIT License
Classifier: Programming Language :: Python
Classifier: Programming Language :: Python :: 3
Requires-Python: >=3.9
License-File: LICENSE
Requires-Dist: Pillow (>=9.2.0)
Requires-Dist: nefile (>=0.9.1)
Requires-Dist: jsons (>=1.6.2)
